simple_swath/__init__.py
simple_swath/_version.py
simple_swath/simple_swath.py
simple_swath-2.0.6.dist-info/LICENCE.txt
simple_swath-2.0.6.dist-info/LICENSE
simple_swath-2.0.6.dist-info/METADATA
simple_swath-2.0.6.dist-info/WHEEL
simple_swath-2.0.6.dist-info/entry_points.txt
simple_swath-2.0.6.dist-info/top_level.txt
simple_swath-2.0.6.dist-info/RECORD
